labdatautils/__init__.py
labdatautils/error_propagation.py
labdatautils/latex_report.py
labdatautils-0.1.2.dist-info/licenses/LICENSE
labdatautils-0.1.2.dist-info/METADATA
labdatautils-0.1.2.dist-info/WHEEL
labdatautils-0.1.2.dist-info/top_level.txt
labdatautils-0.1.2.dist-info/RECORD
