Metadata-Version: 2.4
Name: labdatautils
Version: 0.1.2
Summary: Experimental data utilities: error propagation and LaTeX table generator
Author-email: Pablo Castro Perez <pbl.castroperez@gmail.com>
License: MIT
Project-URL: Homepage, https://github.com/Pablo-CastroPerez/labdatautils
Project-URL: BugTracker, https://github.com/Pablo-CastroPerez/labdatautils/issues
Requires-Python: >=3.8
License-File: LICENSE
Requires-Dist: numpy>=1.22
Dynamic: license-file
